{
	"imgback": "img/highway_back.jpg",
	"imgshapes": "img/highway_shapes.png",
	"shapes": [
		{"name":"btnleft"     , "type":"button"  , "x": 195, "y":  77, "w":105, "h": 73, "xpos":  81, "ypos": 529},
		{"name":"btnmode"     , "type":"button"  , "x": 344, "y":  55, "w": 51, "h": 52, "xpos": 109, "ypos": 211},
		{"name":"btnright1"   , "type":"button"  , "x": 195, "y":   0, "w":109, "h": 77, "xpos":1085, "ypos": 530},
		{"name":"btnset"      , "type":"button"  , "x": 416, "y": 107, "w": 54, "h": 50, "xpos": 107, "ypos": 320},
		{"name":"btnsound"    , "type":"button"  , "x": 344, "y": 256, "w": 60, "h": 48, "xpos": 107, "ypos": 103},
		{"name":"car1"        , "type":"shape"   , "x": 395, "y":  55, "w": 72, "h": 50, "xpos": 409, "ypos": 500},
		{"name":"car2"        , "type":"shape"   , "x": 395, "y":  55, "w": 72, "h": 50, "xpos": 501, "ypos": 501},
		{"name":"car3"        , "type":"shape"   , "x": 395, "y":  55, "w": 72, "h": 50, "xpos": 597, "ypos": 503},
		{"name":"car4"        , "type":"shape"   , "x": 395, "y":  55, "w": 72, "h": 50, "xpos": 693, "ypos": 504},
		{"name":"car5"        , "type":"shape"   , "x": 395, "y":  55, "w": 72, "h": 50, "xpos": 785, "ypos": 507},
		{"name":"cargirl1"    , "type":"shape"   , "x": 344, "y": 107, "w": 72, "h": 50, "xpos": 408, "ypos": 500, "yedit":570},
		{"name":"cargirl2"    , "type":"shape"   , "x": 344, "y": 107, "w": 72, "h": 50, "xpos": 501, "ypos": 501, "yedit":570},
		{"name":"cargirl3"    , "type":"shape"   , "x": 344, "y": 107, "w": 72, "h": 50, "xpos": 597, "ypos": 503, "yedit":570},
		{"name":"cargirl4"    , "type":"shape"   , "x": 344, "y": 107, "w": 72, "h": 50, "xpos": 693, "ypos": 504, "yedit":570},
		{"name":"cargirl5"    , "type":"shape"   , "x": 344, "y": 107, "w": 72, "h": 50, "xpos": 785, "ypos": 507, "yedit":570},
		{"name":"carlifes1"   , "type":"shape"   , "x":  68, "y": 304, "w": 70, "h": 44, "xpos": 370, "ypos": 273},
		{"name":"carlifes2"   , "type":"shape"   , "x": 138, "y": 304, "w": 69, "h": 44, "xpos": 444, "ypos": 274},
		{"name":"carlifes3"   , "type":"shape"   , "x":   0, "y": 304, "w": 68, "h": 46, "xpos": 519, "ypos": 274},
		{"name":"crash1"      , "type":"shape"   , "x":   0, "y": 350, "w": 97, "h": 37, "xpos": 481, "ypos": 469},
		{"name":"crash2"      , "type":"shape"   , "x": 207, "y": 304, "w": 96, "h": 43, "xpos": 593, "ypos": 463},
		{"name":"crash3"      , "type":"shape"   , "x": 376, "y": 304, "w": 87, "h": 38, "xpos": 701, "ypos": 467},
		{"name":"digit0"      , "type":"digit"   , "x": 262, "y": 175, "w": 40, "h": 60, "xpos": 302, "ypos":   0},
		{"name":"digit1"      , "type":"digit"   , "x":   0, "y": 244, "w": 40, "h": 60, "xpos": 342, "ypos":   0},
		{"name":"digit2"      , "type":"digit"   , "x":  40, "y": 244, "w": 40, "h": 60, "xpos": 382, "ypos":   0},
		{"name":"digit3"      , "type":"digit"   , "x":  80, "y": 244, "w": 40, "h": 60, "xpos": 422, "ypos":   0},
		{"name":"digit4"      , "type":"digit"   , "x": 222, "y": 175, "w": 40, "h": 60, "xpos": 462, "ypos":   0},
		{"name":"digit5"      , "type":"digit"   , "x": 160, "y": 244, "w": 40, "h": 60, "xpos": 502, "ypos":   0},
		{"name":"digit6"      , "type":"digit"   , "x": 200, "y": 244, "w": 40, "h": 60, "xpos": 542, "ypos":   0},
		{"name":"digit7"      , "type":"digit"   , "x": 240, "y": 244, "w": 40, "h": 60, "xpos": 582, "ypos":   0},
		{"name":"digit8"      , "type":"digit"   , "x": 120, "y": 244, "w": 40, "h": 60, "xpos": 622, "ypos":   0},
		{"name":"digit9"      , "type":"digit"   , "x": 304, "y":   0, "w": 40, "h": 60, "xpos": 662, "ypos":   0},
		{"name":"digit_"      , "type":"digitpos", "x": 262, "y": 175, "w": 40, "h": 60, "xpos": 425, "ypos": 167},
		{"name":"digit_"      , "type":"digitpos", "x": 262, "y": 175, "w": 40, "h": 60, "xpos": 472, "ypos": 167},
		{"name":"digit_"      , "type":"digitpos", "x": 262, "y": 175, "w": 40, "h": 60, "xpos": 534, "ypos": 167},
		{"name":"digit_"      , "type":"digitpos", "x": 262, "y": 175, "w": 40, "h": 60, "xpos": 582, "ypos": 167},
		{"name":"digit_"      , "type":"digitpos", "x": 262, "y": 175, "w": 40, "h": 60, "xpos": 630, "ypos": 167},
		{"name":"digitbonus0" , "type":"digit"   , "x": 446, "y": 256, "w": 20, "h": 35, "xpos": 342, "ypos":  80},
		{"name":"digitbonus1" , "type":"digit"   , "x": 304, "y": 154, "w": 20, "h": 35, "xpos": 302, "ypos":  80},
		{"name":"digitbonus2" , "type":"digit"   , "x": 324, "y": 154, "w": 20, "h": 35, "xpos": 322, "ypos":  80},
		{"name":"digitbonus3" , "type":"digit"   , "x": 304, "y": 189, "w": 20, "h": 35, "xpos": 362, "ypos":  80},
		{"name":"digitbonus_" , "type":"digitpos", "x": 304, "y": 189, "w": 20, "h": 35, "xpos": 803, "ypos": 246},
		{"name":"digitbonus_" , "type":"digitpos", "x": 304, "y": 189, "w": 20, "h": 35, "xpos": 833, "ypos": 246},
		{"name":"digitbonus_" , "type":"digitpos", "x": 304, "y": 189, "w": 20, "h": 35, "xpos": 863, "ypos": 246},
		{"name":"dog1"        , "type":"shape"   , "x": 329, "y":  60, "w": 11, "h": 17, "xpos": 616, "ypos": 335},
		{"name":"dog2"        , "type":"shape"   , "x": 160, "y":  95, "w": 21, "h": 26, "xpos": 591, "ypos": 364},
		{"name":"dog3"        , "type":"shape"   , "x": 304, "y": 118, "w": 25, "h": 36, "xpos": 562, "ypos": 395},
		{"name":"dog4"        , "type":"shape"   , "x": 344, "y": 157, "w": 32, "h": 50, "xpos": 531, "ypos": 429},
		{"name":"game1"       , "type":"shape"   , "x":   0, "y": 387, "w": 93, "h": 22, "xpos": 435, "ypos": 240},
		{"name":"game2"       , "type":"shape"   , "x": 195, "y": 150, "w": 99, "h": 23, "xpos": 536, "ypos": 241},
		{"name":"gameover"    , "type":"shape"   , "x": 344, "y": 207, "w":105, "h": 49, "xpos": 597, "ypos": 266},
		{"name":"gas"         , "type":"shape"   , "x":  97, "y": 350, "w": 63, "h": 35, "xpos": 833, "ypos": 186},
		{"name":"gas_car"     , "type":"shape"   , "x": 344, "y":   0, "w":126, "h": 55, "xpos": 773, "ypos": 292},
		{"name":"girl1"       , "type":"shape"   , "x": 447, "y": 157, "w": 19, "h": 41, "xpos": 550, "ypos": 325},
		{"name":"girl2"       , "type":"shape"   , "x": 304, "y":  60, "w": 25, "h": 58, "xpos": 518, "ypos": 328},
		{"name":"girl3"       , "type":"shape"   , "x": 122, "y":  95, "w": 38, "h": 79, "xpos": 460, "ypos": 340},
		{"name":"girl4"       , "type":"shape"   , "x":   0, "y":   0, "w": 41, "h": 95, "xpos": 389, "ypos": 363},
		{"name":"girl_dropoff", "type":"shape"   , "x":  41, "y":   0, "w": 34, "h": 95, "xpos": 862, "ypos": 375},
		{"name":"road_left0"  , "type":"shape"   , "x": 329, "y": 118, "w": 13, "h": 10, "xpos": 615, "ypos": 324},
		{"name":"road_left1"  , "type":"shape"   , "x": 324, "y": 189, "w": 19, "h": 17, "xpos": 595, "ypos": 332},
		{"name":"road_left2"  , "type":"shape"   , "x": 160, "y": 121, "w": 34, "h": 23, "xpos": 564, "ypos": 350},
		{"name":"road_left3"  , "type":"shape"   , "x": 303, "y": 304, "w": 73, "h": 40, "xpos": 481, "ypos": 387},
		{"name":"road_left4"  , "type":"shape"   , "x":   0, "y":  95, "w":122, "h": 80, "xpos": 351, "ypos": 441},
		{"name":"road_right0" , "type":"shape"   , "x": 329, "y":  90, "w": 15, "h": 12, "xpos": 642, "ypos": 323},
		{"name":"road_right1" , "type":"shape"   , "x":  75, "y":  81, "w": 16, "h": 11, "xpos": 653, "ypos": 336},
		{"name":"road_right2" , "type":"shape"   , "x": 302, "y": 350, "w": 40, "h": 26, "xpos": 672, "ypos": 348},
		{"name":"road_right3" , "type":"shape"   , "x": 376, "y": 157, "w": 71, "h": 48, "xpos": 716, "ypos": 383},
		{"name":"road_right4" , "type":"shape"   , "x":  75, "y":   0, "w":120, "h": 81, "xpos": 795, "ypos": 442},
		{"name":"setting"     , "type":"shape"   , "x": 342, "y": 350, "w":113, "h": 24, "xpos": 681, "ypos": 183},
		{"name":"sign1"       , "type":"shape"   , "x": 329, "y": 102, "w": 11, "h": 11, "xpos": 630, "ypos": 317},
		{"name":"sign2"       , "type":"shape"   , "x": 449, "y": 243, "w": 14, "h": 13, "xpos": 623, "ypos": 331},
		{"name":"sign3"       , "type":"shape"   , "x": 304, "y": 224, "w": 30, "h": 32, "xpos": 618, "ypos": 355},
		{"name":"sign4"       , "type":"shape"   , "x":  83, "y": 175, "w": 79, "h": 64, "xpos": 595, "ypos": 405},
		{"name":"signdrop1"   , "type":"shape"   , "x": 324, "y": 206, "w": 17, "h": 17, "xpos": 664, "ypos": 325},
		{"name":"signdrop2"   , "type":"shape"   , "x": 304, "y": 256, "w": 32, "h": 27, "xpos": 685, "ypos": 334},
		{"name":"signdrop3"   , "type":"shape"   , "x": 404, "y": 256, "w": 42, "h": 43, "xpos": 728, "ypos": 347},
		{"name":"signdrop4"   , "type":"shape"   , "x": 162, "y": 175, "w": 60, "h": 63, "xpos": 790, "ypos": 374},
		{"name":"time_onoff"  , "type":"shape"   , "x": 205, "y": 350, "w": 50, "h": 28, "xpos": 381, "ypos": 172},
		{"name":"time_pm"     , "type":"shape"   , "x": 160, "y": 350, "w": 45, "h": 29, "xpos": 385, "ypos": 201},
		{"name":"timecolon"   , "type":"shape"   , "x": 449, "y": 207, "w": 13, "h": 36, "xpos": 517, "ypos": 180},
		{"name":"tree1"       , "type":"shape"   , "x": 329, "y":  77, "w": 11, "h": 13, "xpos": 641, "ypos": 336},
		{"name":"tree2"       , "type":"shape"   , "x": 304, "y": 283, "w": 25, "h": 17, "xpos": 656, "ypos": 354},
		{"name":"tree3"       , "type":"shape"   , "x": 255, "y": 350, "w": 47, "h": 28, "xpos": 650, "ypos": 373},
		{"name":"tree4"       , "type":"shape"   , "x":   0, "y": 175, "w": 83, "h": 69, "xpos": 677, "ypos": 407}
	],
	"sequences": [
		{"name": "btnleft"     , "ids": [0]},
		{"name": "btnmode"     , "ids": [1]},
		{"name": "btnright"    , "ids": [2]},
		{"name": "btnset"      , "ids": [3]},
		{"name": "btnsound"    , "ids": [4]},
		{"name": "car"         , "ids": [5, 6, 7, 8, 9, 10, 11, 12, 13, 14]},
		{"name": "carlifes"    , "ids": [15, 16, 17]},
		{"name": "crash"       , "ids": [18, 19, 20]},
		{"name": "dog"         , "ids": [43, 44, 45, 46]},
		{"name": "game"        , "ids": [47, 48]},
		{"name": "gameover"    , "ids": [49]},
		{"name": "gas"         , "ids": [50]},
		{"name": "gas_car"     , "ids": [51]},
		{"name": "girl"        , "ids": [52, 53, 54, 55]},
		{"name": "girl_dropoff", "ids": [56]},
		{"name": "road_left"   , "ids": [57, 58, 59, 60, 61]},
		{"name": "road_right"  , "ids": [62, 63, 64, 65, 66]},
		{"name": "setting"     , "ids": [67]},
		{"name": "sign"        , "ids": [68, 69, 70, 71]},
		{"name": "signdrop"    , "ids": [72, 73, 74, 75]},
		{"name": "time_onoff"  , "ids": [76]},
		{"name": "time_pm"     , "ids": [77]},
		{"name": "timecolon"   , "ids": [78]},
		{"name": "tree"        , "ids": [79, 80, 81, 82]}
	],
	"digits": [
		{"name": "digit"       , "ids": [21, 22, 23, 24, 25, 26, 27, 28, 29, 30], "placeids": [31, 32, 33, 34, 35], "max": "18880" },
		{"name": "digitbonus"  , "ids": [36, 37, 38, 39], "placeids": [40, 41, 42], "max": "111" }
	],
	"buttons": [
		{"name": "left",  "ids": [0], "defaultkey": "left"},
		{"name": "right", "ids": [2], "defaultkey": "right"},
		{"name": "sound", "ids": [4], "defaultkey": "2"},
		{"name": "mode",  "ids": [1], "defaultkey": "1"},
		{"name": "set",   "ids": [3], "defaultkey": "3"}
	],
	"sounds" : [
		{"name": "tick",       "filename": "snd/highway_tick.wav"},
		{"name": "move",       "filename": "snd/highway_move.wav"},
		{"name": "pickup",     "filename": "snd/highway_pickup.wav"},
		{"name": "dropoff",    "filename": "snd/highway_dropoff.wav"},
		{"name": "bonusstart", "filename": "snd/highway_bonnusstart.wav"},
		{"name": "bonuswin",   "filename": "snd/highway_bonuswin.wav"},
		{"name": "bonusalarm", "filename": "snd/highway_bonusalarm.wav"},
		{"name": "crash",      "filename": "snd/highway_crash.wav"}
	]
}